MANIFEST.in
README.rst
setup.py
ecbxrate/__init__.py
ecbxrate/api.py
ecbxrate/tables.py
ecbxrate.egg-info/PKG-INFO
ecbxrate.egg-info/SOURCES.txt
ecbxrate.egg-info/dependency_links.txt
ecbxrate.egg-info/requires.txt
ecbxrate.egg-info/top_level.txt
scripts/ecbxrate
tests/__init__.py
tests/test_fetch.py
tests/test_rates.py