Metadata-Version: 1.1
Name: ecbxrate
Version: 0.2.3
Summary: Exchange rates for Python
Home-page: http://bitbucket.org/al45tair/ecbxrate
Author: Alastair Houghton
Author-email: alastair@alastairs-place.net
License: MIT License
Platform: UNKNOWN
Classifier: Development Status :: 4 - Beta
Classifier: License :: OSI Approved :: MIT License
Classifier: Topic :: Software Development :: Libraries
Provides: ecbxrate
